pymort/__init__.py
pymort/_types.py
pymort/cli.py
pymort/lifetables.py
pymort/pipeline.py
pymort/py.typed
pymort/utils.py
pymort/analysis/__init__.py
pymort/analysis/bootstrap.py
pymort/analysis/fitting.py
pymort/analysis/projections.py
pymort/analysis/reporting.py
pymort/analysis/risk_tools.py
pymort/analysis/scenario.py
pymort/analysis/scenario_analysis.py
pymort/analysis/sensitivities.py
pymort/analysis/smoothing.py
pymort/analysis/validation.py
pymort/interest_rates/__init__.py
pymort/interest_rates/hull_white.py
pymort/models/__init__.py
pymort/models/apc_m3.py
pymort/models/cbd_m5.py
pymort/models/cbd_m6.py
pymort/models/cbd_m7.py
pymort/models/gompertz.py
pymort/models/lc_m1.py
pymort/models/lc_m2.py
pymort/models/utils.py
pymort/pricing/__init__.py
pymort/pricing/hedging.py
pymort/pricing/liabilities.py
pymort/pricing/longevity_bonds.py
pymort/pricing/mortality_derivatives.py
pymort/pricing/risk_neutral.py
pymort/pricing/survivor_swaps.py
pymort/pricing/utils.py
pymort/visualization/__init__.py
pymort/visualization/fans.py
pymort/visualization/lexis.py
pymort_palqc-1.0.6.dist-info/licenses/LICENSE
pymort_palqc-1.0.6.dist-info/METADATA
pymort_palqc-1.0.6.dist-info/WHEEL
pymort_palqc-1.0.6.dist-info/entry_points.txt
pymort_palqc-1.0.6.dist-info/top_level.txt
pymort_palqc-1.0.6.dist-info/RECORD
