Metadata-Version: 2.4
Name: pymort-palqc
Version: 1.0.6
Summary: Longevity bond pricing and mortality modeling toolkit
Author-email: Pierre-Antoine Le Quellec <pierre-antoine.lequellec@unil.ch>
Requires-Python: >=3.10
License-File: LICENSE
Requires-Dist: numpy>=1.26
Requires-Dist: pandas>=2.1
Requires-Dist: scipy>=1.11
Requires-Dist: statsmodels>=0.14
Requires-Dist: typer>=0.12
Requires-Dist: openpyxl>=3.1
Requires-Dist: typing-extensions>=4.7
Provides-Extra: dev
Requires-Dist: pytest>=8.0; extra == "dev"
Requires-Dist: pytest-cov>=5.0; extra == "dev"
Requires-Dist: pytest-xdist>=3.5; extra == "dev"
Requires-Dist: hypothesis>=6.0; extra == "dev"
Requires-Dist: ruff>=0.4; extra == "dev"
Requires-Dist: mypy>=1.9; extra == "dev"
Requires-Dist: pre-commit>=3.6; extra == "dev"
Requires-Dist: pandas-stubs>=2.1.4.240218; extra == "dev"
Requires-Dist: types-setuptools>=69.0; extra == "dev"
Requires-Dist: types-PyYAML>=6.0; extra == "dev"
Requires-Dist: matplotlib>=3.8; extra == "dev"
Requires-Dist: build>=1.1; extra == "dev"
Requires-Dist: twine>=5.0; extra == "dev"
Requires-Dist: scikit-learn>=1.3; extra == "dev"
Requires-Dist: bandit>=1.7; extra == "dev"
Requires-Dist: interrogate>=1.7; extra == "dev"
Requires-Dist: pytest-watch>=4.2; extra == "dev"
Provides-Extra: app
Requires-Dist: streamlit>=1.30; extra == "app"
Dynamic: license-file
